Metadata-Version: 2.1
Name: GAML
Version: 1.0
Summary: Genetic Algorithm Machine Learning
Home-page: https://github.com/orlandoacevedo/GAML
Author: Orlando Acevedo
Author-email: orlando.acevedo@miami.edu
Maintainer: Xiang Zhong
Maintainer-email: xxz385@miami.edu
License: MIT
Keywords: Computational Chemistry Genetic Algorithm Machine Learning
Platform: UNKNOWN
Classifier: Development Status :: 3 - Alpha
Classifier: Environment :: Console
Classifier: Intended Audience :: Developers
Classifier: Topic :: Software Development :: Build Tools
Classifier: Programming Language :: Python :: 3
Classifier: Topic :: Scientific/Engineering :: Chemistry
Classifier: Topic :: Scientific/Engineering :: Visualization
